ilkbyte/__init__.py
ilkbyte/client.py
ilkbyte/exception.py
ilkbyte/session.py
ilkbyte/utils.py
tests/__init__.py
tests/test_client.py
ilkbyte-1.0.2.dist-info/LICENSE
ilkbyte-1.0.2.dist-info/METADATA
ilkbyte-1.0.2.dist-info/WHEEL
ilkbyte-1.0.2.dist-info/top_level.txt
ilkbyte-1.0.2.dist-info/RECORD
