Metadata-Version: 2.1
Name: ilkbyte
Version: 1.0.2
Summary: Ilkbyte python client
Home-page: https://github.com/bkayranci/ilkbyte-python-client
Author: Türkalp Burak Kayrancıoğlu
Author-email: bkayranci@gmail.com
License: UNKNOWN
Platform: UNKNOWN
Classifier: Programming Language :: Python :: 3
Classifier: License :: OSI Approved :: MIT License
Classifier: Operating System :: OS Independent
Requires-Python: >=3.6
Requires-Dist: requests (==2.25.0)
